{
  "storage": [
    {
      "astId": 65604,
      "contract": "contracts/Arbitrum_SpokePool.sol:Arbitrum_SpokePool",
      "label": "_initialized",
      "offset": 0,
      "slot": "0",
      "type": "t_uint8"
    },
    {
      "astId": 65607,
      "contract": "contracts/Arbitrum_SpokePool.sol:Arbitrum_SpokePool",
      "label": "_initializing",
      "offset": 1,
      "slot": "0",
      "type": "t_bool"
    },
    {
      "astId": 65586,
      "contract": "contracts/Arbitrum_SpokePool.sol:Arbitrum_SpokePool",
      "label": "__gap",
      "offset": 0,
      "slot": "1",
      "type": "t_array(t_uint256)50_storage"
    },
    {
      "astId": 65902,
      "contract": "contracts/Arbitrum_SpokePool.sol:Arbitrum_SpokePool",
      "label": "__gap",
      "offset": 0,
      "slot": "51",
      "type": "t_array(t_uint256)50_storage"
    },
    {
      "astId": 65918,
      "contract": "contracts/Arbitrum_SpokePool.sol:Arbitrum_SpokePool",
      "label": "_status",
      "offset": 0,
      "slot": "101",
      "type": "t_uint256"
    },
    {
      "astId": 65987,
      "contract": "contracts/Arbitrum_SpokePool.sol:Arbitrum_SpokePool",
      "label": "__gap",
      "offset": 0,
      "slot": "102",
      "type": "t_array(t_uint256)49_storage"
    },
    {
      "astId": 18018,
      "contract": "contracts/Arbitrum_SpokePool.sol:Arbitrum_SpokePool",
      "label": "__gap",
      "offset": 0,
      "slot": "151",
      "type": "t_array(t_uint256)1000_storage"
    },
    {
      "astId": 17750,
      "contract": "contracts/Arbitrum_SpokePool.sol:Arbitrum_SpokePool",
      "label": "_HASHED_NAME",
      "offset": 0,
      "slot": "1151",
      "type": "t_bytes32"
    },
    {
      "astId": 17752,
      "contract": "contracts/Arbitrum_SpokePool.sol:Arbitrum_SpokePool",
      "label": "_HASHED_VERSION",
      "offset": 0,
      "slot": "1152",
      "type": "t_bytes32"
    },
    {
      "astId": 17851,
      "contract": "contracts/Arbitrum_SpokePool.sol:Arbitrum_SpokePool",
      "label": "__gap",
      "offset": 0,
      "slot": "1153",
      "type": "t_array(t_uint256)1000_storage"
    },
    {
      "astId": 5938,
      "contract": "contracts/Arbitrum_SpokePool.sol:Arbitrum_SpokePool",
      "label": "crossDomainAdmin",
      "offset": 0,
      "slot": "2153",
      "type": "t_address"
    },
    {
      "astId": 5940,
      "contract": "contracts/Arbitrum_SpokePool.sol:Arbitrum_SpokePool",
      "label": "hubPool",
      "offset": 0,
      "slot": "2154",
      "type": "t_address"
    },
    {
      "astId": 5943,
      "contract": "contracts/Arbitrum_SpokePool.sol:Arbitrum_SpokePool",
      "label": "DEPRECATED_wrappedNativeToken",
      "offset": 0,
      "slot": "2155",
      "type": "t_contract(WETH9Interface)13488"
    },
    {
      "astId": 5945,
      "contract": "contracts/Arbitrum_SpokePool.sol:Arbitrum_SpokePool",
      "label": "DEPRECATED_depositQuoteTimeBuffer",
      "offset": 20,
      "slot": "2155",
      "type": "t_uint32"
    },
    {
      "astId": 5947,
      "contract": "contracts/Arbitrum_SpokePool.sol:Arbitrum_SpokePool",
      "label": "numberOfDeposits",
      "offset": 24,
      "slot": "2155",
      "type": "t_uint32"
    },
    {
      "astId": 5949,
      "contract": "contracts/Arbitrum_SpokePool.sol:Arbitrum_SpokePool",
      "label": "pausedFills",
      "offset": 28,
      "slot": "2155",
      "type": "t_bool"
    },
    {
      "astId": 5951,
      "contract": "contracts/Arbitrum_SpokePool.sol:Arbitrum_SpokePool",
      "label": "pausedDeposits",
      "offset": 29,
      "slot": "2155",
      "type": "t_bool"
    },
    {
      "astId": 5955,
      "contract": "contracts/Arbitrum_SpokePool.sol:Arbitrum_SpokePool",
      "label": "rootBundles",
      "offset": 0,
      "slot": "2156",
      "type": "t_array(t_struct(RootBundle)14065_storage)dyn_storage"
    },
    {
      "astId": 5961,
      "contract": "contracts/Arbitrum_SpokePool.sol:Arbitrum_SpokePool",
      "label": "enabledDepositRoutes",
      "offset": 0,
      "slot": "2157",
      "type": "t_mapping(t_address,t_mapping(t_uint256,t_bool))"
    },
    {
      "astId": 5965,
      "contract": "contracts/Arbitrum_SpokePool.sol:Arbitrum_SpokePool",
      "label": "DEPRECATED_relayFills",
      "offset": 0,
      "slot": "2158",
      "type": "t_mapping(t_bytes32,t_uint256)"
    },
    {
      "astId": 5969,
      "contract": "contracts/Arbitrum_SpokePool.sol:Arbitrum_SpokePool",
      "label": "DEPRECATED_fillCounter",
      "offset": 0,
      "slot": "2159",
      "type": "t_mapping(t_address,t_uint256)"
    },
    {
      "astId": 5973,
      "contract": "contracts/Arbitrum_SpokePool.sol:Arbitrum_SpokePool",
      "label": "DEPRECATED_depositCounter",
      "offset": 0,
      "slot": "2160",
      "type": "t_mapping(t_address,t_uint256)"
    },
    {
      "astId": 5977,
      "contract": "contracts/Arbitrum_SpokePool.sol:Arbitrum_SpokePool",
      "label": "DEPRECATED_refundsRequested",
      "offset": 0,
      "slot": "2161",
      "type": "t_mapping(t_bytes32,t_uint256)"
    },
    {
      "astId": 5981,
      "contract": "contracts/Arbitrum_SpokePool.sol:Arbitrum_SpokePool",
      "label": "fillStatuses",
      "offset": 0,
      "slot": "2162",
      "type": "t_mapping(t_bytes32,t_uint256)"
    },
    {
      "astId": 7882,
      "contract": "contracts/Arbitrum_SpokePool.sol:Arbitrum_SpokePool",
      "label": "__gap",
      "offset": 0,
      "slot": "2163",
      "type": "t_array(t_uint256)999_storage"
    },
    {
      "astId": 98,
      "contract": "contracts/Arbitrum_SpokePool.sol:Arbitrum_SpokePool",
      "label": "l2GatewayRouter",
      "offset": 0,
      "slot": "3162",
      "type": "t_address"
    },
    {
      "astId": 102,
      "contract": "contracts/Arbitrum_SpokePool.sol:Arbitrum_SpokePool",
      "label": "whitelistedTokens",
      "offset": 0,
      "slot": "3163",
      "type": "t_mapping(t_address,t_address)"
    }
  ],
  "types": {
    "t_address": {
      "encoding": "inplace",
      "label": "address",
      "numberOfBytes": "20"
    },
    "t_array(t_struct(RootBundle)14065_storage)dyn_storage": {
      "encoding": "dynamic_array",
      "label": "struct SpokePoolInterface.RootBundle[]",
      "numberOfBytes": "32",
      "base": "t_struct(RootBundle)14065_storage"
    },
    "t_array(t_uint256)1000_storage": {
      "encoding": "inplace",
      "label": "uint256[1000]",
      "numberOfBytes": "32000",
      "base": "t_uint256"
    },
    "t_array(t_uint256)49_storage": {
      "encoding": "inplace",
      "label": "uint256[49]",
      "numberOfBytes": "1568",
      "base": "t_uint256"
    },
    "t_array(t_uint256)50_storage": {
      "encoding": "inplace",
      "label": "uint256[50]",
      "numberOfBytes": "1600",
      "base": "t_uint256"
    },
    "t_array(t_uint256)999_storage": {
      "encoding": "inplace",
      "label": "uint256[999]",
      "numberOfBytes": "31968",
      "base": "t_uint256"
    },
    "t_bool": {
      "encoding": "inplace",
      "label": "bool",
      "numberOfBytes": "1"
    },
    "t_bytes32": {
      "encoding": "inplace",
      "label": "bytes32",
      "numberOfBytes": "32"
    },
    "t_contract(WETH9Interface)13488": {
      "encoding": "inplace",
      "label": "contract WETH9Interface",
      "numberOfBytes": "20"
    },
    "t_mapping(t_address,t_address)": {
      "encoding": "mapping",
      "key": "t_address",
      "label": "mapping(address => address)",
      "numberOfBytes": "32",
      "value": "t_address"
    },
    "t_mapping(t_address,t_mapping(t_uint256,t_bool))": {
      "encoding": "mapping",
      "key": "t_address",
      "label": "mapping(address => mapping(uint256 => bool))",
      "numberOfBytes": "32",
      "value": "t_mapping(t_uint256,t_bool)"
    },
    "t_mapping(t_address,t_uint256)": {
      "encoding": "mapping",
      "key": "t_address",
      "label": "mapping(address => uint256)",
      "numberOfBytes": "32",
      "value": "t_uint256"
    },
    "t_mapping(t_bytes32,t_uint256)": {
      "encoding": "mapping",
      "key": "t_bytes32",
      "label": "mapping(bytes32 => uint256)",
      "numberOfBytes": "32",
      "value": "t_uint256"
    },
    "t_mapping(t_uint256,t_bool)": {
      "encoding": "mapping",
      "key": "t_uint256",
      "label": "mapping(uint256 => bool)",
      "numberOfBytes": "32",
      "value": "t_bool"
    },
    "t_mapping(t_uint256,t_uint256)": {
      "encoding": "mapping",
      "key": "t_uint256",
      "label": "mapping(uint256 => uint256)",
      "numberOfBytes": "32",
      "value": "t_uint256"
    },
    "t_struct(RootBundle)14065_storage": {
      "encoding": "inplace",
      "label": "struct SpokePoolInterface.RootBundle",
      "numberOfBytes": "96",
      "members": [
        {
          "astId": 14058,
          "contract": "contracts/Arbitrum_SpokePool.sol:Arbitrum_SpokePool",
          "label": "slowRelayRoot",
          "offset": 0,
          "slot": "0",
          "type": "t_bytes32"
        },
        {
          "astId": 14060,
          "contract": "contracts/Arbitrum_SpokePool.sol:Arbitrum_SpokePool",
          "label": "relayerRefundRoot",
          "offset": 0,
          "slot": "1",
          "type": "t_bytes32"
        },
        {
          "astId": 14064,
          "contract": "contracts/Arbitrum_SpokePool.sol:Arbitrum_SpokePool",
          "label": "claimedBitmap",
          "offset": 0,
          "slot": "2",
          "type": "t_mapping(t_uint256,t_uint256)"
        }
      ]
    },
    "t_uint256": {
      "encoding": "inplace",
      "label": "uint256",
      "numberOfBytes": "32"
    },
    "t_uint32": {
      "encoding": "inplace",
      "label": "uint32",
      "numberOfBytes": "4"
    },
    "t_uint8": {
      "encoding": "inplace",
      "label": "uint8",
      "numberOfBytes": "1"
    }
  }
}
